nutcracker.pypy39-pp73-x86-linux-gnu.so
squirrel_decompiler-0.0.2.dist-info/METADATA
squirrel_decompiler-0.0.2.dist-info/WHEEL
squirrel_decompiler-0.0.2.dist-info/RECORD
squirrel_decompiler-0.0.2.dist-info/top_level.txt
squirrel_decompiler-0.0.2.dist-info/LICENSE
