Metadata-Version: 2.1
Name: squirrel_decompiler
Version: 0.0.2
Summary: NutCracker - Squirrel-Lang bytecode cracker, used to decompile .cnut bytecode
Home-page: https://github.com/shabbywu/NutCracker
Author: shabbywu
Author-email: shabbywu@qq.com
Requires-Python: >=3.7
Provides-Extra: test
License-File: LICENSE
